{
  "members": [
    {
      "id": "1234",
      "email": "ant@gmail.com",
      "password": "1234",
      "name": "안태현"
    },
    {
      "id": "5678",
      "email": "woori@naver.com",
      "password": "5678",
      "name": "우리은행"
    }
  ],
  "transactions": [
    {
      "id": "1",
      "userId": "1234",
      "income": true,
      "outcome": false,
      "expense": 3000000,
      "category": "월급",
      "date": "2025-04-01"
    },
    {
      "id": "2",
      "userId": "1234",
      "income": true,
      "outcome": false,
      "expense": 150000,
      "category": "부수입",
      "date": "2025-04-08"
    },
    {
      "id": "3",
      "userId": "1234",
      "income": true,
      "outcome": false,
      "expense": 100000,
      "category": "금융소득",
      "date": "2025-04-12"
    },
    {
      "id": "4",
      "userId": "1234",
      "income": false,
      "outcome": true,
      "expense": 50000,
      "category": "식비",
      "date": "2025-04-02"
    },
    {
      "id": "5",
      "userId": "1234",
      "income": false,
      "outcome": true,
      "expense": 30000,
      "category": "교통",
      "date": "2025-04-03"
    },
    {
      "id": "6",
      "userId": "1234",
      "income": false,
      "outcome": true,
      "expense": 70000,
      "category": "문화생활",
      "date": "2025-04-05"
    },
    {
      "id": "7",
      "userId": "1234",
      "income": false,
      "outcome": true,
      "expense": 150000,
      "category": "생활비",
      "date": "2025-04-09"
    },
    {
      "id": "8",
      "userId": "1234",
      "income": false,
      "outcome": true,
      "expense": 90000,
      "category": "패션",
      "date": "2025-04-10"
    },
    {
      "id": "9",
      "userId": "1234",
      "income": false,
      "outcome": true,
      "expense": 20000,
      "category": "기타",
      "date": "2025-04-11"
    },
    {
      "id": "10",
      "userId": "5678",
      "income": true,
      "outcome": false,
      "expense": 2800000,
      "category": "월급",
      "date": "2025-04-01"
    },
    {
      "id": "11",
      "userId": "5678",
      "income": true,
      "outcome": false,
      "expense": 120000,
      "category": "부수입",
      "date": "2025-04-06"
    },
    {
      "id": "12",
      "userId": "5678",
      "income": false,
      "outcome": true,
      "expense": 45000,
      "category": "식비",
      "date": "2025-04-02"
    },
    {
      "id": "13",
      "userId": "5678",
      "income": false,
      "outcome": true,
      "expense": 28000,
      "category": "교통",
      "date": "2025-04-05"
    },
    {
      "id": "14",
      "userId": "5678",
      "income": false,
      "outcome": true,
      "expense": 60000,
      "category": "생활비",
      "date": "2025-04-08"
    },
    {
      "id": "15",
      "userId": "5678",
      "income": false,
      "outcome": true,
      "expense": 110000,
      "category": "패션",
      "date": "2025-04-12"
    },
    {
      "id": "21a7",
      "userId": "1234",
      "date": "2025-04-16",
      "expense": 150000,
      "category": "기타",
      "memo": "기타를 샀음",
      "income": false,
      "outcome": true
    }
  ]
}
